.gitignore
LICENSE
README.md
gen-api.sh
setup.py
contrail_api_cli_extra/__init__.py
contrail_api_cli_extra/utils.py
contrail_api_cli_extra.egg-info/PKG-INFO
contrail_api_cli_extra.egg-info/SOURCES.txt
contrail_api_cli_extra.egg-info/dependency_links.txt
contrail_api_cli_extra.egg-info/entry_points.txt
contrail_api_cli_extra.egg-info/requires.txt
contrail_api_cli_extra.egg-info/top_level.txt
contrail_api_cli_extra/clean/__init__.py
contrail_api_cli_extra/clean/clean_obj_mandatory_fields.py
contrail_api_cli_extra/clean/fqn.py
contrail_api_cli_extra/clean/orphaned_acl.py
contrail_api_cli_extra/clean/project.py
contrail_api_cli_extra/clean/refs.py
contrail_api_cli_extra/clean/rt.py
contrail_api_cli_extra/clean/si.py
contrail_api_cli_extra/clean/subnet.py
contrail_api_cli_extra/fix/__init__.py
contrail_api_cli_extra/fix/fix_fip_locks.py
contrail_api_cli_extra/fix/fix_sg.py
contrail_api_cli_extra/fix/fix_subnets.py
contrail_api_cli_extra/fix/fix_vn_id.py
contrail_api_cli_extra/fix/fix_zk_ip.py
contrail_api_cli_extra/fix/ri.py
contrail_api_cli_extra/migration/__init__.py
contrail_api_cli_extra/migration/host_routes.py
contrail_api_cli_extra/migration/lb.py
contrail_api_cli_extra/migration/rt.py
contrail_api_cli_extra/migration/si.py
contrail_api_cli_extra/misc/__init__.py
contrail_api_cli_extra/misc/apply_sg.py
contrail_api_cli_extra/misc/check_bad_refs.py
contrail_api_cli_extra/misc/dot.py
contrail_api_cli_extra/misc/graph.py
contrail_api_cli_extra/misc/manage_rt.py
contrail_api_cli_extra/misc/rpf.py
contrail_api_cli_extra/misc/vm.py
contrail_api_cli_extra/provision/__init__.py
contrail_api_cli_extra/provision/analytics.py
contrail_api_cli_extra/provision/bgp_router.py
contrail_api_cli_extra/provision/common.py
contrail_api_cli_extra/provision/config.py
contrail_api_cli_extra/provision/dns_nameserver.py
contrail_api_cli_extra/provision/encapsulation.py
contrail_api_cli_extra/provision/global_asn.py
contrail_api_cli_extra/provision/linklocal.py
contrail_api_cli_extra/provision/lr.py
contrail_api_cli_extra/provision/provision.py
contrail_api_cli_extra/provision/route_target.py
contrail_api_cli_extra/provision/service_appliance_set.py
contrail_api_cli_extra/provision/sg.py
contrail_api_cli_extra/provision/subnet.py
