Metadata-Version: 1.2
Name: contrail-api-cli-extra
Version: 0.5.9
Summary: Supplementary commands for contrail-api-cli
Home-page: http://www.github.com/cloudwatt/contrail-api-cli-extra
Author: Jean-Philippe Braun
Author-email: jean-philippe.braun@cloudwatt.com
Maintainer: Jean-Philippe Braun
Maintainer-email: jean-philippe.braun@cloudwatt.com
License: MIT
Platform: UNKNOWN
Classifier: Development Status :: 3 - Alpha
Classifier: Intended Audience :: Developers
Classifier: Topic :: Software Development :: User Interfaces
Classifier: License :: OSI Approved :: MIT License
Classifier: Programming Language :: Python :: 2.7
Classifier: Programming Language :: Python :: 3.4
